fedctl/__init__.py
fedctl/__main__.py
fedctl/cli.py
fedctl/build/__init__.py
fedctl/build/build.py
fedctl/build/dockerfile.py
fedctl/build/errors.py
fedctl/build/inspect.py
fedctl/build/push.py
fedctl/build/state.py
fedctl/build/tagging.py
fedctl/commands/__init__.py
fedctl/commands/address.py
fedctl/commands/build.py
fedctl/commands/configure.py
fedctl/commands/deploy.py
fedctl/commands/destroy.py
fedctl/commands/discover.py
fedctl/commands/doctor.py
fedctl/commands/inspect.py
fedctl/commands/local.py
fedctl/commands/ping.py
fedctl/commands/register.py
fedctl/commands/run.py
fedctl/commands/status.py
fedctl/config/__init__.py
fedctl/config/io.py
fedctl/config/merge.py
fedctl/config/paths.py
fedctl/config/repo.py
fedctl/config/schema.py
fedctl/deploy/__init__.py
fedctl/deploy/destroy.py
fedctl/deploy/errors.py
fedctl/deploy/naming.py
fedctl/deploy/plan.py
fedctl/deploy/render.py
fedctl/deploy/resolve.py
fedctl/deploy/spec.py
fedctl/deploy/status.py
fedctl/deploy/submit.py
fedctl/nomad/__init__.py
fedctl/nomad/client.py
fedctl/nomad/errors.py
fedctl/nomad/nodeview.py
fedctl/project/__init__.py
fedctl/project/errors.py
fedctl/project/flwr_inspect.py
fedctl/project/pyproject_patch.py
fedctl/state/__init__.py
fedctl/state/errors.py
fedctl/state/manifest.py
fedctl/state/store.py
fedctl/util/console.py
fedctl-0.1.0.dist-info/METADATA
fedctl-0.1.0.dist-info/WHEEL
fedctl-0.1.0.dist-info/entry_points.txt
fedctl-0.1.0.dist-info/top_level.txt
fedctl-0.1.0.dist-info/RECORD
