Metadata-Version: 2.4
Name: fedctl
Version: 0.1.0
Summary: Federated control CLI
Requires-Python: >=3.11
Requires-Dist: typer>=0.12.0
Requires-Dist: tomlkit>=0.12.0
Requires-Dist: rich>=13.0.0
Requires-Dist: httpx>=0.27.0
Requires-Dist: jinja2>=3.1.0
Requires-Dist: PyYAML>=6.0.0
